ezmsg/panel/__init__.py
ezmsg/panel/__version__.py
ezmsg/panel/application.py
ezmsg/panel/lineplot.py
ezmsg/panel/py.typed
ezmsg/panel/recorder.py
ezmsg/panel/replay.py
ezmsg/panel/scrollinglineplot.py
ezmsg/panel/spectrum.py
ezmsg/panel/tabbedapp.py
ezmsg/panel/timeseriesplot.py
ezmsg/panel/util.py
ezmsg_panel-0.6.7.dist-info/METADATA
ezmsg_panel-0.6.7.dist-info/WHEEL
ezmsg_panel-0.6.7.dist-info/licenses/LICENSE
ezmsg_panel-0.6.7.dist-info/RECORD
