Metadata-Version: 2.4
Name: ezmsg-panel
Version: 0.6.7
Summary: Panel patterns for ezmsg systems
Author-email: Griffin Milsap <griffin.milsap@gmail.com>
License-Expression: MIT
License-File: LICENSE
Requires-Python: <3.13,>=3.10.15
Requires-Dist: ezmsg>=3.6.0
Requires-Dist: panel>=1.5.3
Provides-Extra: sigproc
Requires-Dist: ezmsg-sigproc<2.0,>=1.8.2; extra == 'sigproc'
